compconf/__init__.py
compconf/__main__.py
compconf-0.6.5.dist-info/licenses/LICENSE
compconf-0.6.5.dist-info/METADATA
compconf-0.6.5.dist-info/WHEEL
compconf-0.6.5.dist-info/top_level.txt
compconf-0.6.5.dist-info/RECORD
