Metadata-Version: 2.4
Name: compconf
Version: 0.6.5
Summary: compconf enables flexible, type-rich comptime configuration of Cerebras Software Language (CSL) projects
Author-email: Matthew Andres Moreno <m.more500@gmail.com>
License: MIT license
Project-URL: homepage, https://github.com/mmore500/compconf
Project-URL: repository, https://github.com/mmore500/compconf.git
Keywords: compconf
Classifier: Development Status :: 2 - Pre-Alpha
Classifier: Intended Audience :: Developers
Classifier: License :: OSI Approved :: MIT License
Classifier: Natural Language :: English
Classifier: Programming Language :: Python :: 3
Classifier: Programming Language :: Python :: 3.8
Classifier: Programming Language :: Python :: 3.9
Classifier: Programming Language :: Python :: 3.10
Classifier: Programming Language :: Python :: 3.11
Classifier: Programming Language :: Python :: 3.12
Classifier: Programming Language :: Python :: 3.13
Requires-Python: >=3.8
License-File: LICENSE
Requires-Dist: jq
Dynamic: license-file
